setup.py
aria_plugin/__init__.py
aria_plugin/constants.py
aria_plugin/environment.py
aria_plugin/exceptions.py
aria_plugin/executor.py
aria_plugin/operations.py
aria_plugin/utils.py
cloudify_aria_plugin.egg-info/PKG-INFO
cloudify_aria_plugin.egg-info/SOURCES.txt
cloudify_aria_plugin.egg-info/dependency_links.txt
cloudify_aria_plugin.egg-info/requires.txt
cloudify_aria_plugin.egg-info/top_level.txt