Metadata-Version: 1.0
Name: cloudify-aria-plugin
Version: 1.1.0
Summary: Cloudify plugin for ARIA.
Home-page: UNKNOWN
Author: cloudify
Author-email: cosmo-admin@gigaspaces.com
License: LICENSE
Platform: UNKNOWN
